odoo/addons/data_encryption/README.rst
odoo/addons/data_encryption/__init__.py
odoo/addons/data_encryption/__manifest__.py
odoo/addons/data_encryption/i18n/ca.po
odoo/addons/data_encryption/i18n/data_encryption.pot
odoo/addons/data_encryption/i18n/es.po
odoo/addons/data_encryption/i18n/it.po
odoo/addons/data_encryption/models/__init__.py
odoo/addons/data_encryption/models/encrypted_data.py
odoo/addons/data_encryption/readme/CONFIGURE.rst
odoo/addons/data_encryption/readme/CONTRIBUTORS.rst
odoo/addons/data_encryption/readme/DESCRIPTION.rst
odoo/addons/data_encryption/readme/ROADMAP.rst
odoo/addons/data_encryption/security/ir.model.access.csv
odoo/addons/data_encryption/static/description/icon.png
odoo/addons/data_encryption/static/description/index.html
odoo/addons/data_encryption/tests/__init__.py
odoo/addons/data_encryption/tests/common.py
odoo/addons/data_encryption/tests/test_data_encrypt.py
odoo14_addon_data_encryption-14.0.1.0.1.dev10.dist-info/METADATA
odoo14_addon_data_encryption-14.0.1.0.1.dev10.dist-info/WHEEL
odoo14_addon_data_encryption-14.0.1.0.1.dev10.dist-info/top_level.txt
odoo14_addon_data_encryption-14.0.1.0.1.dev10.dist-info/RECORD
