Metadata-Version: 2.1
Name: odoo14-addon-data_encryption
Version: 14.0.1.0.1.dev10
Summary: Store accounts and credentials encrypted by environment
Home-page: https://github.com/OCA/server-env
Author: Akretion, Odoo Community Association (OCA)
Author-email: support@odoo-community.org
License: AGPL-3
Classifier: Programming Language :: Python
Classifier: Framework :: Odoo
Classifier: Framework :: Odoo :: 14.0
Classifier: License :: OSI Approved :: GNU Affero General Public License v3
Classifier: Development Status :: 3 - Alpha
Requires-Python: >=3.6
Requires-Dist: cryptography
Requires-Dist: odoo<14.1dev,>=14.0a
